{
    "flow_volume": 200,
    "flow_duration": 0,
    "flow_rate": 6000000,
    "sleep_time": 10,
    "dns_interval": -30,
    "ntp_interval": -30,
    "ports": {
        "67": 12,
        "10001": 444,
        "40274": 1,
        "123": 60,
        "59960": 56,
        "42153": 1,
        "null": 28,
        "34557": 1,
        "80": 12,
        "55003": 1,
        "52761": 1,
        "55492": 1,
        "39147": 1,
        "40822": 1,
        "53486": 1,
        "41340": 1,
        "56974": 1,
        "40817": 1,
        "51915": 1,
        "40187": 1,
        "48789": 1,
        "34569": 1,
        "34848": 1,
        "47650": 1,
        "52425": 1,
        "43481": 1,
        "51610": 1,
        "54857": 1,
        "33073": 1,
        "51567": 1,
        "33098": 1,
        "59215": 1,
        "60766": 1,
        "56276": 1,
        "43290": 1,
        "57361": 1,
        "58830": 1,
        "59084": 1,
        "51735": 1,
        "41551": 1,
        "45420": 1,
        "59809": 1,
        "52683": 1,
        "43371": 1,
        "45752": 1,
        "42700": 1,
        "38706": 1,
        "36196": 1,
        "34595": 1,
        "51986": 1,
        "45534": 1,
        "49701": 1,
        "45061": 1,
        "51116": 1,
        "57119": 1,
        "38076": 1,
        "37933": 1,
        "51036": 1,
        "37484": 1,
        "39039": 1,
        "35355": 1,
        "39591": 1,
        "37171": 1,
        "44178": 1,
        "35466": 1,
        "39565": 1,
        "56736": 1,
        "54826": 1,
        "60404": 1,
        "48906": 1,
        "59433": 1,
        "54662": 1,
        "56308": 1,
        "56322": 1,
        "44936": 1,
        "53300": 1,
        "49699": 1,
        "60291": 1
    },
    "domains": {
        "time.nist.gov": 60,
        "connect.insteon.com": 12
    },
    "ciphers": {}
}