{
    "flow_volume": 100,
    "flow_duration": 10,
    "flow_rate": 6000000,
    "sleep_time": 10,
    "dns_interval": 10,
    "ntp_interval": 10,
    "ports": {
        "68": 25,
        "123": 159,
        "null": 521,
        "44307": 44,
        "5222": 161,
        "443": 221,
        "1900": 480,
        "18389": 6,
        "4500": 176,
        "25050": 6,
        "33434": 266,
        "10001": 617,
        "52180": 36,
        "67": 16,
        "3080": 23,
        "5000": 46,
        "56777": 1,
        "56700": 60,
        "5228": 51,
        "3478": 27,
        "6804": 1,
        "59012": 1,
        "80": 50,
        "52242": 1,
        "3122": 2,
        "58453": 1,
        "30590": 1,
        "2366": 27,
        "8090": 12,
        "47628": 1,
        "30617": 2,
        "57829": 40,
        "38660": 1,
        "41693": 1,
        "60669": 1,
        "38341": 1,
        "50196": 1,
        "34111": 1,
        "16301": 1,
        "58502": 7,
        "37958": 1,
        "45311": 1,
        "22213": 1,
        "59639": 1,
        "34959": 1,
        "30618": 2,
        "35624": 1,
        "36147": 1,
        "58326": 1,
        "60428": 1,
        "49692": 1,
        "43046": 1,
        "6806": 1,
        "57550": 1,
        "37840": 1,
        "47015": 1,
        "34642": 1,
        "30619": 2,
        "38371": 1,
        "37204": 1,
        "37749": 1,
        "3101": 2,
        "52291": 1,
        "52340": 1,
        "32828": 1,
        "50077": 1,
        "57831": 1,
        "20219": 1,
        "13072": 1,
        "13921": 1,
        "56475": 1,
        "30620": 2,
        "56012": 1,
        "38351": 1,
        "45055": 1,
        "37459": 1,
        "50735": 1,
        "6808": 1,
        "33309": 1,
        "41137": 1,
        "43196": 1,
        "41937": 1,
        "53339": 1,
        "30621": 2,
        "38151": 1,
        "54005": 1,
        "48378": 1,
        "36475": 1,
        "53354": 1,
        "57994": 1,
        "42608": 1,
        "58540": 1,
        "36582": 1,
        "52474": 1,
        "48997": 1,
        "30622": 2,
        "35000": 1,
        "50478": 1,
        "47442": 1,
        "55036": 1,
        "37303": 1,
        "6810": 1,
        "40115": 1,
        "55033": 1,
        "56408": 1,
        "45932": 1,
        "30623": 2,
        "54623": 1,
        "56391": 1,
        "54066": 1,
        "41703": 1,
        "36074": 1,
        "45553": 1,
        "47044": 1,
        "26353": 1,
        "16236": 1,
        "7275": 2,
        "21024": 1,
        "9043": 1,
        "21578": 1,
        "37714": 1,
        "43231": 1,
        "30624": 2,
        "37668": 1,
        "55265": 1,
        "50080": 1,
        "47765": 1,
        "33012": 1,
        "39870": 1,
        "33477": 1,
        "6812": 1,
        "42961": 1,
        "33648": 1,
        "33274": 1,
        "37355": 1,
        "46309": 1,
        "33095": 1,
        "58308": 1,
        "35154": 17,
        "37407": 1,
        "30625": 2,
        "59366": 1,
        "44939": 1,
        "53637": 1,
        "38970": 1,
        "58797": 1,
        "36921": 1,
        "53981": 1,
        "47669": 1,
        "51882": 1,
        "30626": 2,
        "15490": 1,
        "33607": 1,
        "41363": 1,
        "34889": 1,
        "6814": 1,
        "58733": 1,
        "49890": 1,
        "42713": 1,
        "47735": 1,
        "34136": 1,
        "48871": 1,
        "57082": 1,
        "36354": 1,
        "30627": 2,
        "57876": 1,
        "54774": 1,
        "42185": 1,
        "36534": 1,
        "41787": 1,
        "54865": 1,
        "8470": 1,
        "17078": 1,
        "25243": 1,
        "21383": 1,
        "18950": 1,
        "59813": 1,
        "58438": 1,
        "34575": 1,
        "41738": 1,
        "54080": 1,
        "30628": 2,
        "47119": 1
    },
    "domains": {
        "netcom.netatmo.net": 14,
        "time.nist.gov": 60,
        "pool.ntp.org": 30,
        "connect.insteon.com": 12,
        "www.belkin.com": 4,
        "d3gjecg2uu2eaq.cloudfront.net": 4,
        "apicom.netatmo.net": 2,
        "www.example.com": 24,
        "www.example.net": 24,
        "www.example.org": 24,
        "173.199.154.195.in-addr.arpa": 1,
        "sip.invoxia.com": 9,
        "a.config.skype.com": 3,
        "device-metrics-us.amazon.com": 5,
        "resolver.msg.xiaomi.net": 2,
        "connectivitycheck.gstatic.com": 4,
        "BCMLS2.glpals.com": 2,
        "service.game-mode.net": 1,
        "mtalk.google.com": 2,
        "pindorama.amazon.com": 1,
        "www.meethue.com": 1
    },
    "ciphers": {
        "[\"c014\", \"c00a\", \"0039\", \"0038\", \"0037\", \"0036\", \"0088\", \"0087\", \"0086\", \"0085\", \"c00f\", \"c005\", \"0035\", \"0084\", \"c013\", \"c009\", \"0033\", \"0032\", \"0031\", \"0030\", \"009a\", \"0099\", \"0098\", \"0097\", \"0045\", \"0044\", \"0043\", \"0042\", \"c00e\", \"c004\", \"002f\", \"0096\", \"0041\", \"0007\", \"c011\", \"c007\", \"c00c\", \"c002\", \"0005\", \"0004\", \"c012\", \"c008\", \"0016\", \"0013\", \"0010\", \"000d\", \"c00d\", \"c003\", \"000a\", \"0015\", \"0012\", \"000f\", \"000c\", \"0009\", \"00ff\"]": 4,
        "[\"c030\", \"c02c\", \"c028\", \"c024\", \"c014\", \"c00a\", \"c022\", \"c021\", \"00a3\", \"009f\", \"006b\", \"006a\", \"0039\", \"0038\", \"c032\", \"c02e\", \"c02a\", \"c026\", \"c00f\", \"c005\", \"009d\", \"003d\", \"0035\", \"c012\", \"c008\", \"c01c\", \"c01b\", \"0016\", \"0013\", \"c00d\", \"c003\", \"000a\", \"c02f\", \"c02b\", \"c027\", \"c023\", \"c013\", \"c009\", \"c01f\", \"c01e\", \"00a2\", \"009e\", \"0067\", \"0040\", \"0033\", \"0032\", \"c031\", \"c02d\", \"c029\", \"c025\", \"c00e\", \"c004\", \"009c\", \"003c\", \"002f\", \"00ff\"]": 1,
        "[\"cca9\", \"cc14\", \"c02b\", \"c02c\", \"cca8\", \"cc13\", \"c02f\", \"c030\", \"009e\", \"009f\", \"c009\", \"c00a\", \"c013\", \"c014\", \"0033\", \"0039\", \"009c\", \"009d\", \"002f\", \"0035\"]": 2,
        "[\"c030\", \"c02c\", \"c028\", \"c024\", \"c014\", \"c00a\", \"00a5\", \"00a3\", \"00a1\", \"009f\", \"006b\", \"006a\", \"0069\", \"0068\", \"0039\", \"0038\", \"0037\", \"0036\", \"0088\", \"0087\", \"0086\", \"0085\", \"c032\", \"c02e\", \"c02a\", \"c026\", \"c00f\", \"c005\", \"009d\", \"003d\", \"0035\", \"0084\", \"c02f\", \"c02b\", \"c027\", \"c023\", \"c013\", \"c009\", \"00a4\", \"00a2\", \"00a0\", \"009e\", \"0067\", \"0040\", \"003f\", \"003e\", \"0033\", \"0032\", \"0031\", \"0030\", \"009a\", \"0099\", \"0098\", \"0097\", \"0045\", \"0044\", \"0043\", \"0042\", \"c031\", \"c02d\", \"c029\", \"c025\", \"c00e\", \"c004\", \"009c\", \"003c\", \"002f\", \"0096\", \"0041\", \"0007\", \"c011\", \"c007\", \"c00c\", \"c002\", \"0005\", \"0004\", \"c012\", \"c008\", \"0016\", \"0013\", \"0010\", \"000d\", \"c00d\", \"c003\", \"000a\", \"0015\", \"0012\", \"000f\", \"000c\", \"0009\", \"00ff\"]": 2
    }
}