{
    "flow_volume": 100,
    "flow_duration": 0,
    "flow_rate": 6000000,
    "sleep_time": 10,
    "dns_interval": 10,
    "ntp_interval": 10,
    "ports": {
        "null": 29,
        "67": 12,
        "10001": 442,
        "41311": 1,
        "123": 60,
        "57584": 1,
        "59960": 15,
        "39685": 1,
        "80": 12,
        "40420": 1,
        "51431": 1,
        "37118": 1,
        "48182": 1,
        "55978": 1,
        "40451": 1,
        "50003": 1,
        "46318": 1,
        "35431": 1,
        "34199": 1,
        "58959": 1,
        "48356": 1,
        "41629": 1,
        "46214": 1,
        "41689": 1,
        "42244": 1,
        "43007": 1,
        "53455": 1,
        "32907": 1,
        "40065": 1,
        "59793": 1,
        "49395": 1,
        "39986": 1,
        "56807": 1,
        "57881": 1,
        "42699": 1,
        "37812": 1,
        "51130": 1,
        "57513": 1,
        "40955": 1,
        "41869": 1,
        "43579": 1,
        "59126": 1,
        "43460": 1,
        "52960": 1,
        "35899": 1,
        "33225": 1,
        "55675": 1,
        "39834": 1,
        "36000": 1,
        "56328": 1,
        "58945": 1,
        "40321": 1,
        "44860": 1,
        "59090": 1,
        "57276": 1,
        "51247": 1,
        "42868": 1,
        "55037": 1,
        "37987": 1,
        "37716": 1,
        "56231": 1,
        "58512": 1,
        "45884": 1,
        "58081": 1,
        "59313": 1,
        "54460": 1,
        "56707": 1,
        "60470": 1,
        "47744": 1,
        "49428": 1,
        "40779": 1,
        "58238": 1,
        "40742": 1,
        "34620": 1,
        "59301": 1,
        "35169": 1,
        "38509": 1,
        "39943": 1
    },
    "domains": {
        "time.nist.gov": 60,
        "connect.insteon.com": 12
    },
    "ciphers": {}
}