{
    "flow_volume": 900,
    "flow_duration": 60,
    "flow_rate": 20,
    "sleep_time": 10,
    "dns_interval": 10,
    "ntp_interval": -1,
    "ports": {
        "5222": 43,
        "57924": 1,
        "80": 16,
        "32801": 1,
        "59621": 1,
        "40179": 15,
        "37378": 1,
        "51424": 1,
        "53213": 1,
        "56287": 1,
        "53307": 1,
        "49719": 1,
        "55921": 1,
        "57325": 1,
        "47741": 1,
        "49570": 1,
        "59454": 1,
        "34066": 1,
        "45630": 1
    },
    "domains": {
        "scalews.withings.net": 16
    },
    "ciphers": {}
}