{
    "flow_volume": 200,
    "flow_duration": 0,
    "flow_rate": 6000000,
    "sleep_time": 10,
    "dns_interval": 10,
    "ntp_interval": 10,
    "ports": {
        "null": 29,
        "51630": 1,
        "123": 60,
        "10001": 461,
        "59960": 19,
        "35481": 1,
        "59111": 1,
        "48832": 1,
        "59138": 1,
        "55515": 1,
        "80": 12,
        "48461": 1,
        "34025": 1,
        "41157": 1,
        "67": 12,
        "56784": 1,
        "45285": 1,
        "57884": 1,
        "42271": 1,
        "48629": 1,
        "48184": 1,
        "50173": 1,
        "51677": 1,
        "36211": 1,
        "43798": 1,
        "50969": 1,
        "57282": 1,
        "38271": 1,
        "35332": 1,
        "41578": 1,
        "38939": 1,
        "36013": 1,
        "52787": 1,
        "57332": 1,
        "49195": 1,
        "35100": 1,
        "57461": 1,
        "47145": 1,
        "35164": 1,
        "42337": 1,
        "55292": 1,
        "59050": 1,
        "56475": 1,
        "57165": 1,
        "33875": 1,
        "43206": 1,
        "45398": 1,
        "46817": 1,
        "52930": 1,
        "42657": 1,
        "44120": 1,
        "49185": 1,
        "34492": 1,
        "38518": 1,
        "52630": 1,
        "58151": 1,
        "45597": 1,
        "52079": 1,
        "50749": 1,
        "59202": 1,
        "60800": 1,
        "38875": 1,
        "58362": 1,
        "49768": 1,
        "39582": 1,
        "36926": 1,
        "58095": 1,
        "60322": 1,
        "54593": 1,
        "57215": 1,
        "37597": 1,
        "43696": 1,
        "59421": 1,
        "47254": 1,
        "33572": 1,
        "35950": 1,
        "35986": 1,
        "35388": 1
    },
    "domains": {
        "time.nist.gov": 60,
        "connect.insteon.com": 12
    },
    "ciphers": {}
}