{
    "flow_volume": 200,
    "flow_duration": 0,
    "flow_rate": 6000000,
    "sleep_time": 10,
    "dns_interval": 10,
    "ntp_interval": 10,
    "ports": {
        "10001": 464,
        "null": 29,
        "57689": 1,
        "123": 60,
        "59960": 23,
        "51031": 1,
        "37170": 1,
        "48392": 1,
        "80": 12,
        "44566": 1,
        "54576": 1,
        "67": 12,
        "49070": 1,
        "42465": 1,
        "50927": 1,
        "48432": 1,
        "38794": 1,
        "59861": 1,
        "60156": 1,
        "41611": 1,
        "36323": 1,
        "54279": 1,
        "52958": 1,
        "49040": 1,
        "48314": 1,
        "54031": 1,
        "49133": 1,
        "33852": 1,
        "34263": 1,
        "60615": 1,
        "39578": 1,
        "36156": 1,
        "34668": 1,
        "41438": 1,
        "41655": 1,
        "48682": 1,
        "52802": 1,
        "41363": 1,
        "55622": 1,
        "56180": 1,
        "39835": 1,
        "35787": 1,
        "42928": 1,
        "44858": 1,
        "59748": 1,
        "50401": 1,
        "34788": 1,
        "56281": 1,
        "49205": 1,
        "35765": 1,
        "35332": 1,
        "58509": 1,
        "54643": 1,
        "57668": 1,
        "46775": 1,
        "46875": 1,
        "60307": 1,
        "35017": 1,
        "58311": 1,
        "54100": 1,
        "47974": 1,
        "37195": 1,
        "38159": 1,
        "34032": 1,
        "36659": 1,
        "34616": 1,
        "34852": 1,
        "51676": 1,
        "46776": 1,
        "58287": 1,
        "54188": 1,
        "48983": 1,
        "58671": 1,
        "47024": 1,
        "47487": 1,
        "42533": 1,
        "37650": 1,
        "48809": 1
    },
    "domains": {
        "time.nist.gov": 60,
        "connect.insteon.com": 12
    },
    "ciphers": {}
}