{
    "flow_volume": 100,
    "flow_duration": 10,
    "flow_rate": 6000000,
    "sleep_time": 10,
    "dns_interval": 10,
    "ntp_interval": 10,
    "ports": {
        "33434": 268,
        "null": 515,
        "4500": 178,
        "443": 219,
        "1900": 481,
        "56700": 60,
        "5222": 341,
        "47689": 42,
        "123": 155,
        "5228": 19,
        "6151": 1,
        "10001": 629,
        "8090": 12,
        "32194": 2,
        "46327": 1,
        "38572": 44,
        "3478": 27,
        "58304": 47,
        "39070": 1,
        "3080": 24,
        "5000": 48,
        "55961": 1,
        "2182": 22,
        "35156": 1,
        "80": 67,
        "37243": 1,
        "45216": 1,
        "57648": 1,
        "47255": 1,
        "52130": 1,
        "13032": 1,
        "16562": 1,
        "11253": 1,
        "20865": 1,
        "37668": 1,
        "43761": 8,
        "32195": 2,
        "46024": 1,
        "33360": 1,
        "38324": 1,
        "60535": 1,
        "67": 7,
        "36629": 1,
        "56364": 1,
        "39534": 1,
        "36016": 1,
        "49680": 1,
        "68": 7,
        "22119": 1,
        "6249": 1,
        "17846": 1,
        "7275": 6,
        "14549": 1,
        "17546": 1,
        "2295": 1,
        "27042": 1,
        "12747": 1,
        "25879": 1,
        "45648": 1,
        "6153": 1,
        "32196": 2,
        "33009": 1,
        "55439": 1,
        "5351": 2,
        "49856": 1,
        "48065": 1,
        "42656": 1,
        "56475": 1,
        "57113": 1,
        "55913": 1,
        "32782": 1,
        "39458": 1,
        "3128": 2,
        "57553": 1,
        "58085": 1,
        "38284": 1,
        "52205": 1,
        "33586": 1,
        "60923": 1,
        "39342": 1,
        "57255": 1,
        "38150": 1,
        "59282": 1,
        "32197": 2,
        "44427": 1,
        "33691": 1,
        "36450": 1,
        "39546": 1,
        "49720": 1,
        "35189": 1,
        "11678": 1,
        "12618": 1,
        "25106": 1,
        "30831": 1,
        "41101": 1,
        "45630": 1,
        "34452": 2,
        "41830": 1,
        "50412": 1,
        "40617": 1,
        "4144": 1,
        "31258": 1,
        "3011": 1,
        "14935": 1,
        "17332": 1,
        "17026": 1,
        "41563": 1,
        "6155": 1,
        "32198": 2,
        "59284": 1,
        "55310": 1,
        "56736": 1,
        "52313": 1,
        "58927": 1,
        "56933": 1,
        "36457": 1,
        "50305": 1,
        "36064": 1,
        "59717": 1,
        "42780": 1,
        "47025": 1,
        "32199": 2,
        "42723": 1,
        "36181": 1,
        "37709": 1,
        "44413": 1,
        "47418": 1,
        "33942": 1,
        "47626": 1,
        "33680": 1,
        "3152": 1,
        "30386": 1,
        "16611": 1,
        "15014": 1,
        "33705": 1,
        "3397": 1,
        "39612": 1,
        "6157": 1,
        "32200": 2,
        "44380": 1,
        "45170": 1,
        "38049": 1,
        "38032": 1,
        "41704": 1,
        "35278": 1,
        "58637": 1,
        "56244": 1,
        "54204": 1,
        "41598": 1,
        "54984": 1,
        "47248": 1,
        "49319": 1,
        "32201": 2,
        "32202": 2,
        "50366": 1,
        "50843": 1,
        "44792": 1,
        "50955": 1,
        "53697": 1,
        "46033": 1,
        "52811": 1,
        "45178": 1,
        "41355": 1,
        "36621": 1,
        "37519": 1,
        "63202": 1,
        "36520": 1,
        "55104": 1,
        "56450": 1,
        "6159": 1,
        "32203": 2,
        "58465": 1,
        "58042": 2,
        "55773": 1,
        "38614": 1,
        "56904": 1,
        "53718": 1,
        "52549": 18,
        "44807": 1,
        "50847": 1,
        "47987": 1,
        "56905": 1,
        "33437": 1,
        "36289": 1,
        "48041": 1,
        "41903": 1,
        "56347": 1,
        "47494": 1,
        "56282": 1,
        "56104": 1,
        "11470": 1,
        "55126": 1,
        "32204": 2,
        "42374": 1,
        "44703": 1,
        "38693": 1,
        "60943": 1,
        "34839": 1,
        "37502": 1,
        "52880": 1,
        "45393": 1,
        "60261": 1,
        "54862": 1,
        "36430": 1,
        "48696": 1,
        "35439": 1,
        "44039": 1,
        "37792": 1,
        "6161": 1,
        "32205": 2,
        "51899": 1,
        "41641": 1,
        "43990": 1,
        "50711": 1,
        "57486": 1,
        "34317": 1,
        "44901": 1,
        "59384": 1,
        "47769": 1,
        "37331": 1,
        "46941": 1,
        "58161": 1,
        "42003": 1,
        "40753": 1,
        "16548": 1,
        "57596": 1,
        "32206": 2,
        "44256": 1,
        "56149": 1,
        "59143": 1,
        "42108": 1,
        "35978": 1,
        "56294": 1,
        "35932": 1,
        "55676": 1,
        "52707": 1,
        "39734": 1,
        "56891": 1,
        "59040": 1,
        "55167": 1
    },
    "domains": {
        "pool.ntp.org": 36,
        "time.nist.gov": 60,
        "www.example.com": 24,
        "www.example.net": 24,
        "www.example.org": 24,
        "connect.insteon.com": 12,
        "mobile.pipe.aria.microsoft.com": 12,
        "a.config.skype.com": 8,
        "sip.invoxia.com": 10,
        "device-metrics-us.amazon.com": 4,
        "connectivitycheck.gstatic.com": 12,
        "resolver.msg.xiaomi.net": 6,
        "mtalk.google.com": 6,
        "b.config.skype.com": 5,
        "xmpp.samsungsmartcam.com": 1,
        "media.samsungsmartcam.com": 1,
        "scalews.withings.net": 13,
        "www.belkin.com": 3,
        "d3gjecg2uu2eaq.cloudfront.net": 3,
        "BCMLS2.glpals.com": 4,
        "service.game-mode.net": 1,
        "pindorama.amazon.com": 1,
        "www.meethue.com": 1,
        "apicom.netatmo.net": 1
    },
    "ciphers": {
        "[\"c014\", \"c00a\", \"0039\", \"0038\", \"0037\", \"0036\", \"0088\", \"0087\", \"0086\", \"0085\", \"c00f\", \"c005\", \"0035\", \"0084\", \"c013\", \"c009\", \"0033\", \"0032\", \"0031\", \"0030\", \"009a\", \"0099\", \"0098\", \"0097\", \"0045\", \"0044\", \"0043\", \"0042\", \"c00e\", \"c004\", \"002f\", \"0096\", \"0041\", \"0007\", \"c011\", \"c007\", \"c00c\", \"c002\", \"0005\", \"0004\", \"c012\", \"c008\", \"0016\", \"0013\", \"0010\", \"000d\", \"c00d\", \"c003\", \"000a\", \"0015\", \"0012\", \"000f\", \"000c\", \"0009\", \"00ff\"]": 4,
        "[\"cca9\", \"cc14\", \"c02b\", \"c02c\", \"cca8\", \"cc13\", \"c02f\", \"c030\", \"009e\", \"009f\", \"c009\", \"c00a\", \"c013\", \"c014\", \"0033\", \"0039\", \"009c\", \"009d\", \"002f\", \"0035\"]": 6,
        "[\"c014\", \"c00a\", \"c022\", \"c021\", \"0039\", \"0038\", \"0088\", \"0087\", \"c019\", \"c020\", \"c00f\", \"c005\", \"0035\", \"0084\", \"c012\", \"c008\", \"c01c\", \"c01b\", \"0016\", \"0013\", \"c017\", \"c01a\", \"c00d\", \"c003\", \"000a\", \"c013\", \"c009\", \"c01f\", \"c01e\", \"0033\", \"0032\", \"009a\", \"0099\", \"0045\", \"0044\", \"c018\", \"c01d\", \"c00e\", \"c004\", \"002f\", \"0096\", \"0041\", \"c011\", \"c007\", \"c016\", \"c00c\", \"c002\", \"0005\", \"00ff\"]": 1,
        "[\"c030\", \"c02c\", \"c028\", \"c024\", \"c014\", \"c00a\", \"c022\", \"c021\", \"00a3\", \"009f\", \"006b\", \"006a\", \"0039\", \"0038\", \"c032\", \"c02e\", \"c02a\", \"c026\", \"c00f\", \"c005\", \"009d\", \"003d\", \"0035\", \"c012\", \"c008\", \"c01c\", \"c01b\", \"0016\", \"0013\", \"c00d\", \"c003\", \"000a\", \"c02f\", \"c02b\", \"c027\", \"c023\", \"c013\", \"c009\", \"c01f\", \"c01e\", \"00a2\", \"009e\", \"0067\", \"0040\", \"0033\", \"0032\", \"c031\", \"c02d\", \"c029\", \"c025\", \"c00e\", \"c004\", \"009c\", \"003c\", \"002f\", \"00ff\"]": 1,
        "[\"c030\", \"c02c\", \"c028\", \"c024\", \"c014\", \"c00a\", \"00a5\", \"00a3\", \"00a1\", \"009f\", \"006b\", \"006a\", \"0069\", \"0068\", \"0039\", \"0038\", \"0037\", \"0036\", \"0088\", \"0087\", \"0086\", \"0085\", \"c032\", \"c02e\", \"c02a\", \"c026\", \"c00f\", \"c005\", \"009d\", \"003d\", \"0035\", \"0084\", \"c02f\", \"c02b\", \"c027\", \"c023\", \"c013\", \"c009\", \"00a4\", \"00a2\", \"00a0\", \"009e\", \"0067\", \"0040\", \"003f\", \"003e\", \"0033\", \"0032\", \"0031\", \"0030\", \"009a\", \"0099\", \"0098\", \"0097\", \"0045\", \"0044\", \"0043\", \"0042\", \"c031\", \"c02d\", \"c029\", \"c025\", \"c00e\", \"c004\", \"009c\", \"003c\", \"002f\", \"0096\", \"0041\", \"0007\", \"c011\", \"c007\", \"c00c\", \"c002\", \"0005\", \"0004\", \"c012\", \"c008\", \"0016\", \"0013\", \"0010\", \"000d\", \"c00d\", \"c003\", \"000a\", \"0015\", \"0012\", \"000f\", \"000c\", \"0009\", \"00ff\"]": 2
    }
}