{
    "flow_volume": 1900,
    "flow_duration": 60,
    "flow_rate": 40,
    "sleep_time": 10,
    "dns_interval": 10,
    "ntp_interval": -1,
    "ports": {
        "5222": 36,
        "55887": 22,
        "60957": 1,
        "80": 10,
        "42841": 1,
        "48106": 1,
        "33356": 1,
        "53920": 1,
        "49567": 1,
        "41871": 1,
        "57489": 1,
        "38032": 1,
        "55692": 1
    },
    "domains": {
        "scalews.withings.net": 10
    },
    "ciphers": {}
}