{
    "flow_volume": 0,
    "flow_duration": 60,
    "flow_rate": 0,
    "sleep_time": 10,
    "dns_interval": 10,
    "ntp_interval": -1,
    "ports": {
        "40933": 53,
        "59863": 1,
        "80": 14,
        "37807": 1,
        "54561": 1,
        "1935": 19,
        "43743": 1,
        "33465": 1,
        "50062": 1,
        "60722": 1,
        "39757": 1,
        "45058": 1,
        "47107": 1,
        "53484": 1,
        "45276": 1,
        "50414": 1,
        "39819": 1
    },
    "domains": {
        "babyws.withings.net": 14
    },
    "ciphers": {}
}