{
    "flow_volume": 200,
    "flow_duration": 0,
    "flow_rate": 6000000,
    "sleep_time": 10,
    "dns_interval": 10,
    "ntp_interval": 10,
    "ports": {
        "59960": 34,
        "36580": 1,
        "123": 60,
        "null": 29,
        "10001": 457,
        "55518": 1,
        "45445": 1,
        "55252": 1,
        "41570": 1,
        "80": 12,
        "49483": 1,
        "49064": 1,
        "49562": 1,
        "49259": 1,
        "67": 12,
        "55251": 1,
        "52862": 1,
        "37870": 1,
        "36039": 1,
        "38243": 1,
        "39880": 1,
        "40226": 1,
        "52642": 1,
        "47013": 1,
        "50699": 1,
        "34394": 1,
        "56368": 1,
        "56240": 1,
        "48248": 1,
        "33619": 1,
        "33833": 1,
        "47915": 1,
        "37935": 1,
        "39398": 1,
        "40945": 1,
        "60914": 1,
        "49021": 1,
        "52785": 1,
        "57898": 1,
        "49215": 1,
        "34430": 1,
        "39573": 1,
        "51672": 1,
        "57598": 1,
        "55148": 1,
        "36906": 1,
        "59646": 1,
        "33440": 1,
        "35375": 1,
        "58610": 1,
        "60340": 1,
        "51863": 1,
        "42538": 1,
        "42894": 1,
        "55899": 1,
        "34822": 1,
        "58233": 1,
        "46797": 1,
        "45306": 1,
        "10240": 2,
        "41451": 1,
        "34549": 1,
        "34488": 1,
        "34522": 1,
        "57512": 1,
        "42869": 1,
        "59852": 1,
        "36676": 1,
        "57147": 1,
        "42676": 1,
        "54509": 1,
        "47601": 1,
        "46463": 1,
        "39279": 1,
        "39658": 1,
        "50880": 1,
        "45848": 1,
        "54936": 1,
        "56291": 1
    },
    "domains": {
        "time.nist.gov": 60,
        "connect.insteon.com": 12
    },
    "ciphers": {}
}