{
    "flow_volume": 200,
    "flow_duration": 10,
    "flow_rate": 10,
    "sleep_time": 10,
    "dns_interval": 10,
    "ntp_interval": 10,
    "ports": {
        "33434": 149,
        "34523": 44,
        "123": 51,
        "443": 41,
        "null": 37,
        "46754": 1,
        "80": 36,
        "33808": 1,
        "36088": 1,
        "56093": 1,
        "54017": 1,
        "34499": 1,
        "40938": 1,
        "45770": 1,
        "55256": 1,
        "52464": 1,
        "42054": 1,
        "47920": 1,
        "55165": 1,
        "54197": 1,
        "51583": 1,
        "52653": 1,
        "56402": 1,
        "60010": 1,
        "60315": 1,
        "60921": 1,
        "41577": 1,
        "50885": 1,
        "45385": 1,
        "55095": 1,
        "58772": 1,
        "40492": 1,
        "40539": 1,
        "42298": 1,
        "49975": 1,
        "34033": 1,
        "38203": 1,
        "33698": 1,
        "36230": 1,
        "37258": 1,
        "51374": 1,
        "37949": 1,
        "59103": 1,
        "52591": 8,
        "1900": 1,
        "54470": 1,
        "54653": 1,
        "58662": 1,
        "38904": 1,
        "57756": 1,
        "33882": 1,
        "34128": 1,
        "39054": 1
    },
    "domains": {
        "www.example.com": 24,
        "www.example.net": 24,
        "www.example.org": 24,
        "device-metrics-us.amazon.com": 6,
        "pindorama.amazon.com": 1,
        "www.meethue.com": 1
    },
    "ciphers": {
        "[\"c014\", \"c00a\", \"0039\", \"0038\", \"0037\", \"0036\", \"0088\", \"0087\", \"0086\", \"0085\", \"c00f\", \"c005\", \"0035\", \"0084\", \"c013\", \"c009\", \"0033\", \"0032\", \"0031\", \"0030\", \"009a\", \"0099\", \"0098\", \"0097\", \"0045\", \"0044\", \"0043\", \"0042\", \"c00e\", \"c004\", \"002f\", \"0096\", \"0041\", \"0007\", \"c011\", \"c007\", \"c00c\", \"c002\", \"0005\", \"0004\", \"c012\", \"c008\", \"0016\", \"0013\", \"0010\", \"000d\", \"c00d\", \"c003\", \"000a\", \"0015\", \"0012\", \"000f\", \"000c\", \"0009\", \"00ff\"]": 4,
        "[\"c030\", \"c02c\", \"c028\", \"c024\", \"c014\", \"c00a\", \"00a5\", \"00a3\", \"00a1\", \"009f\", \"006b\", \"006a\", \"0069\", \"0068\", \"0039\", \"0038\", \"0037\", \"0036\", \"0088\", \"0087\", \"0086\", \"0085\", \"c032\", \"c02e\", \"c02a\", \"c026\", \"c00f\", \"c005\", \"009d\", \"003d\", \"0035\", \"0084\", \"c02f\", \"c02b\", \"c027\", \"c023\", \"c013\", \"c009\", \"00a4\", \"00a2\", \"00a0\", \"009e\", \"0067\", \"0040\", \"003f\", \"003e\", \"0033\", \"0032\", \"0031\", \"0030\", \"009a\", \"0099\", \"0098\", \"0097\", \"0045\", \"0044\", \"0043\", \"0042\", \"c031\", \"c02d\", \"c029\", \"c025\", \"c00e\", \"c004\", \"009c\", \"003c\", \"002f\", \"0096\", \"0041\", \"0007\", \"c011\", \"c007\", \"c00c\", \"c002\", \"0005\", \"0004\", \"c012\", \"c008\", \"0016\", \"0013\", \"0010\", \"000d\", \"c00d\", \"c003\", \"000a\", \"0015\", \"0012\", \"000f\", \"000c\", \"0009\", \"00ff\"]": 2
    }
}