{
    "flow_volume": 300,
    "flow_duration": 0,
    "flow_rate": 10,
    "sleep_time": 10,
    "dns_interval": 10,
    "ntp_interval": -1,
    "ports": {
        "9277": 1,
        "4432": 1,
        "11499": 1,
        "7119": 1,
        "null": 22,
        "38047": 1,
        "39791": 2,
        "53": 1,
        "7074": 1,
        "5706": 1,
        "5228": 6,
        "14299": 1,
        "6458": 1,
        "26336": 1,
        "67": 3,
        "68": 3,
        "7275": 3,
        "10914": 1,
        "5427": 1,
        "1864": 1,
        "80": 6,
        "13005": 1,
        "9280": 1,
        "25088": 1,
        "6850": 1,
        "22549": 1,
        "8131": 1,
        "35935": 1,
        "49930": 1,
        "16082": 1,
        "23565": 1,
        "25772": 1,
        "15777": 1,
        "7738": 1,
        "4613": 1,
        "23998": 1,
        "25056": 1,
        "47425": 1,
        "50839": 3,
        "27921": 1,
        "5760": 1,
        "31323": 1,
        "51848": 1,
        "38350": 2,
        "31291": 2,
        "25022": 1,
        "4236": 1,
        "32952": 1,
        "15656": 1,
        "33048": 1,
        "13665": 1,
        "31858": 1,
        "11668": 1,
        "6772": 1
    },
    "domains": {
        "mobile.pipe.aria.microsoft.com": 12,
        "a.config.skype.com": 6,
        "connectivitycheck.gstatic.com": 8,
        "mtalk.google.com": 5,
        "b.config.skype.com": 4,
        "BCMLS2.glpals.com": 2,
        "resolver.msg.xiaomi.net": 3,
        "app.chat.xiaomi.net": 1,
        "gllto2.glpals.com": 1
    },
    "ciphers": {
        "[\"cca9\", \"cc14\", \"c02b\", \"c02c\", \"cca8\", \"cc13\", \"c02f\", \"c030\", \"009e\", \"009f\", \"c009\", \"c00a\", \"c013\", \"c014\", \"0033\", \"0039\", \"009c\", \"009d\", \"002f\", \"0035\"]": 5
    }
}