{
    "flow_volume": 900,
    "flow_duration": 60,
    "flow_rate": 20,
    "sleep_time": 10,
    "dns_interval": 10,
    "ntp_interval": -1,
    "ports": {
        "40179": 17,
        "5222": 37,
        "41418": 1,
        "80": 10,
        "45497": 1,
        "36615": 1,
        "33919": 1,
        "55142": 1,
        "40024": 1,
        "36519": 1,
        "53067": 1,
        "56176": 1,
        "50845": 1
    },
    "domains": {
        "scalews.withings.net": 10
    },
    "ciphers": {}
}