{
    "flow_volume": 1900,
    "flow_duration": 60,
    "flow_rate": 40,
    "sleep_time": 10,
    "dns_interval": 10,
    "ntp_interval": -1,
    "ports": {
        "5222": 38,
        "35813": 1,
        "80": 22,
        "52251": 1,
        "36036": 1,
        "56729": 1,
        "56409": 1,
        "44955": 1,
        "55887": 19,
        "45285": 1,
        "57093": 1,
        "55274": 1,
        "44604": 1,
        "42184": 1,
        "51701": 1,
        "41911": 1,
        "45058": 1,
        "33689": 1,
        "40022": 1,
        "56308": 1,
        "35075": 1,
        "36081": 1,
        "67": 1,
        "50809": 1,
        "36114": 1,
        "55318": 1
    },
    "domains": {
        "scalews.withings.net": 22
    },
    "ciphers": {}
}