{
    "flow_volume": 200,
    "flow_duration": 0,
    "flow_rate": 10,
    "sleep_time": 10,
    "dns_interval": 10,
    "ntp_interval": 10,
    "ports": {
        "56700": 28,
        "30646": 2,
        "123": 12,
        "30647": 2,
        "28046": 2,
        "30648": 2,
        "30649": 2,
        "30650": 2,
        "30651": 2,
        "30652": 2,
        "30653": 2,
        "30654": 2,
        "30655": 2,
        "2952": 1,
        "30656": 2,
        "30657": 2,
        "30658": 2
    },
    "domains": {
        "pool.ntp.org": 24,
        "v2.broker.lifx.co": 2
    },
    "ciphers": {
        "[\"0035\", \"002f\", \"0004\"]": 1
    }
}