{
    "flow_volume": 100,
    "flow_duration": 10,
    "flow_rate": 800000,
    "sleep_time": 10,
    "dns_interval": 10,
    "ntp_interval": -1,
    "ports": {
        "1900": 112,
        "null": 114,
        "5222": 71,
        "3080": 23,
        "49152": 42,
        "37112": 1,
        "80": 7,
        "35081": 1,
        "465": 7,
        "59285": 1,
        "59057": 1,
        "54525": 1,
        "49982": 1,
        "47021": 1,
        "35510": 1,
        "44904": 1,
        "48457": 1,
        "51213": 1,
        "41348": 1,
        "46600": 1,
        "51517": 1
    },
    "domains": {
        "www.samsungsmartcam.com": 10,
        "smtp.gmail.com": 14
    },
    "ciphers": {}
}