{
    "flow_volume": 200,
    "flow_duration": 0,
    "flow_rate": 10,
    "sleep_time": 10,
    "dns_interval": -30,
    "ntp_interval": -30,
    "ports": {
        "10001": 419,
        "59971": 1,
        "123": 60,
        "59960": 76,
        "35936": 1,
        "null": 28,
        "40336": 1,
        "42561": 1,
        "80": 12,
        "58707": 1,
        "46453": 1,
        "48926": 1,
        "67": 12,
        "52731": 1,
        "48677": 1,
        "49050": 1,
        "39423": 1,
        "57547": 1,
        "57836": 1,
        "50962": 1,
        "33259": 1,
        "41001": 1,
        "45677": 1,
        "46925": 1,
        "53517": 1,
        "35798": 1,
        "53366": 1,
        "45153": 1,
        "35073": 1,
        "33285": 1,
        "36701": 1,
        "36206": 1,
        "38250": 1,
        "48804": 1,
        "38821": 1,
        "58046": 1,
        "55651": 1,
        "39961": 1,
        "50304": 1,
        "42915": 1,
        "59584": 1,
        "53493": 1,
        "50184": 1,
        "39919": 1,
        "41377": 1,
        "54294": 1,
        "55227": 1,
        "59040": 1,
        "55875": 1,
        "49304": 1,
        "59924": 1,
        "41360": 1,
        "48538": 1,
        "56913": 1,
        "55211": 1,
        "56325": 1,
        "57973": 1,
        "39363": 1,
        "52156": 1,
        "51374": 1,
        "35066": 1,
        "43445": 1,
        "34284": 1,
        "49157": 1,
        "56234": 1,
        "34343": 1,
        "56452": 1,
        "58213": 1,
        "55828": 1,
        "37320": 1,
        "41135": 1,
        "51742": 1,
        "37421": 1,
        "43770": 1,
        "52537": 1,
        "35690": 1,
        "46229": 1,
        "56853": 1
    },
    "domains": {
        "time.nist.gov": 60,
        "connect.insteon.com": 12
    },
    "ciphers": {}
}