{
    "flow_volume": 200,
    "flow_duration": 0,
    "flow_rate": 6000000,
    "sleep_time": 10,
    "dns_interval": -30,
    "ntp_interval": -30,
    "ports": {
        "10001": 484,
        "59960": 68,
        "58594": 1,
        "123": 60,
        "35336": 1,
        "null": 32,
        "53824": 1,
        "45999": 1,
        "80": 12,
        "55460": 1,
        "60360": 1,
        "36169": 1,
        "41526": 1,
        "67": 12,
        "48415": 1,
        "57074": 1,
        "42972": 1,
        "52869": 1,
        "58983": 1,
        "40595": 1,
        "41813": 1,
        "45656": 1,
        "42730": 1,
        "36981": 1,
        "57862": 1,
        "58736": 1,
        "39260": 1,
        "47077": 1,
        "58240": 1,
        "51355": 1,
        "60923": 1,
        "50946": 1,
        "35630": 1,
        "45442": 1,
        "59588": 1,
        "50127": 1,
        "37062": 1,
        "43393": 1,
        "44929": 1,
        "38876": 1,
        "33126": 1,
        "46754": 1,
        "53348": 1,
        "48496": 1,
        "48298": 1,
        "47414": 1,
        "43573": 1,
        "43927": 1,
        "54709": 1,
        "42946": 1,
        "56215": 1,
        "40403": 1,
        "46747": 1,
        "50433": 1,
        "36991": 1,
        "36909": 1,
        "45851": 1,
        "53093": 1,
        "46003": 1,
        "56672": 1,
        "52697": 1,
        "35455": 1,
        "56924": 1,
        "60774": 1,
        "59004": 1,
        "36133": 1,
        "34499": 1,
        "43195": 1,
        "38180": 1,
        "39867": 1,
        "49174": 1,
        "59593": 1,
        "37658": 1,
        "48431": 1,
        "38778": 1,
        "38118": 1,
        "35927": 1,
        "33589": 1
    },
    "domains": {
        "time.nist.gov": 60,
        "connect.insteon.com": 12
    },
    "ciphers": {}
}