{
    "flow_volume": 0,
    "flow_duration": 10,
    "flow_rate": 0,
    "sleep_time": 10,
    "dns_interval": 10,
    "ntp_interval": -1,
    "ports": {
        "14866": 1,
        "443": 82,
        "null": 23,
        "5228": 22,
        "80": 6,
        "35428": 1,
        "46875": 5,
        "5222": 5,
        "57824": 1,
        "41062": 1,
        "993": 6,
        "49222": 1,
        "42975": 3,
        "67": 4,
        "68": 4,
        "7275": 4,
        "46675": 1,
        "43917": 1,
        "54307": 1,
        "53369": 1,
        "44124": 1,
        "43648": 1,
        "52049": 1,
        "43207": 1,
        "49879": 1,
        "56165": 1,
        "58751": 1,
        "35851": 1,
        "64362": 1,
        "36666": 3,
        "34627": 1,
        "46879": 4,
        "44224": 1,
        "50321": 1,
        "36036": 1,
        "46958": 1,
        "32809": 2,
        "35034": 1,
        "45043": 1,
        "50444": 1,
        "46880": 2,
        "48781": 1,
        "55696": 1,
        "42124": 1,
        "61100": 1,
        "56288": 1,
        "48014": 1,
        "39247": 1,
        "43369": 1,
        "54108": 1,
        "61382": 1,
        "54587": 1,
        "60468": 1,
        "51796": 1,
        "48996": 1,
        "62411": 1,
        "55788": 1,
        "50326": 1,
        "46881": 3,
        "40954": 1,
        "4755": 1,
        "6687": 1,
        "4170": 1,
        "56880": 1,
        "50779": 2,
        "50508": 1,
        "56227": 1,
        "8813": 1,
        "31033": 1,
        "23050": 1,
        "9705": 1,
        "12220": 1,
        "3599": 1,
        "12392": 1,
        "14458": 1,
        "10084": 1,
        "23678": 1,
        "5039": 1,
        "8819": 1,
        "28930": 1,
        "7186": 1,
        "9461": 1,
        "8229": 1,
        "56260": 1,
        "14220": 1,
        "4228": 1,
        "46889": 5,
        "50331": 1,
        "34373": 1,
        "47106": 1,
        "35438": 1,
        "37079": 2,
        "53": 2,
        "14806": 1,
        "23848": 1,
        "22476": 1,
        "23753": 1,
        "30322": 1,
        "18090": 1,
        "4303": 1,
        "28061": 1,
        "29827": 1,
        "13687": 1,
        "24135": 1,
        "6697": 1,
        "9804": 1,
        "32904": 1,
        "18480": 1,
        "44585": 1,
        "46850": 1,
        "46894": 3,
        "50336": 1,
        "15184": 1,
        "52393": 1,
        "42327": 1,
        "32901": 1,
        "60176": 2,
        "52296": 1,
        "17518": 1,
        "41268": 1,
        "32580": 1,
        "15340": 1,
        "38950": 1
    },
    "domains": {
        "www.google.com": 1,
        "connectivitycheck.gstatic.com": 8,
        "BCMLS2.glpals.com": 2,
        "s-usc1c-nss-117.firebaseio.com": 7,
        "mtalk.google.com": 4,
        "api.samsungosp.com": 4,
        "apps.skype.com": 4,
        "az361816.vo.msecnd.net": 4,
        "api.tplinkra.com": 5,
        "tplinkkasa.firebaseio.com": 4,
        "ws.invoxia.io": 3,
        "mobile.pipe.aria.microsoft.com": 10,
        "sip.invoxia.com": 5,
        "clients3.google.com": 3,
        "imap.gmail.com": 4,
        "android.clients.google.com": 1,
        "www.google.com.au": 1,
        "a.config.skype.com": 2,
        "b.config.skype.com": 2,
        "play.googleapis.com": 1
    },
    "ciphers": {
        "[\"cca9\", \"cc14\", \"c02b\", \"c02c\", \"cca8\", \"cc13\", \"c02f\", \"c030\", \"009e\", \"009f\", \"c009\", \"c00a\", \"c013\", \"c014\", \"0033\", \"0039\", \"009c\", \"009d\", \"002f\", \"0035\"]": 9,
        "[\"c02b\", \"c02c\", \"c02f\", \"c030\", \"009e\", \"009f\", \"c009\", \"c00a\", \"c013\", \"c014\", \"0033\", \"0039\", \"c007\", \"c011\", \"009c\", \"009d\", \"002f\", \"0035\", \"0005\", \"00ff\"]": 46,
        "[\"c02b\", \"c02f\", \"009e\", \"c00a\", \"c009\", \"c013\", \"c014\", \"0033\", \"0039\", \"009c\", \"002f\", \"0035\", \"00ff\"]": 6,
        "[\"c030\", \"c02c\", \"c028\", \"c024\", \"c014\", \"c00a\", \"c032\", \"c02e\", \"c02a\", \"c026\", \"c00f\", \"c005\", \"009d\", \"003d\", \"0035\", \"c02f\", \"c02b\", \"c027\", \"c023\", \"c013\", \"c009\", \"c031\", \"c02d\", \"c029\", \"c025\", \"c00e\", \"c004\", \"009c\", \"003c\", \"002f\", \"c012\", \"c008\", \"c00d\", \"c003\", \"000a\", \"00ff\"]": 8,
        "[\"cca9\", \"cca8\", \"cc14\", \"cc13\", \"c02b\", \"c02f\", \"c02c\", \"c030\", \"c009\", \"c013\", \"c00a\", \"c014\", \"009c\", \"009d\", \"002f\", \"0035\", \"000a\"]": 1
    }
}