{
    "flow_volume": 800,
    "flow_duration": 0,
    "flow_rate": 20,
    "sleep_time": 10,
    "dns_interval": 10,
    "ntp_interval": -1,
    "ports": {
        "5222": 40,
        "49908": 4,
        "39057": 1,
        "51366": 1,
        "80": 18,
        "42080": 1,
        "39856": 1,
        "50674": 1,
        "35480": 1,
        "50957": 1,
        "57921": 1,
        "58526": 1,
        "51217": 1,
        "52255": 1,
        "34006": 1,
        "43036": 1,
        "51078": 1,
        "56973": 1,
        "49184": 1,
        "40117": 21,
        "54773": 1,
        "54132": 1,
        "39680": 1,
        "67": 1,
        "37429": 1,
        "41188": 1,
        "40777": 1,
        "56936": 1,
        "39708": 1,
        "52566": 1,
        "58787": 1,
        "50280": 1
    },
    "domains": {
        "scalews.withings.net": 18,
        "xmpp.withings.net": 8
    },
    "ciphers": {}
}